flask_fastapi/__init__.py
flask_fastapi/constants.py
flask_fastapi/exceptions.py
flask_fastapi/flask_fastapi.py
flask_fastapi/json.py
flask_fastapi/redoc.html
flask_fastapi/schema.py
flask_fastapi/swaggerui.html
flask_fastapi/templates/redoc.html
flask_fastapi/templates/swaggerui.html
flask_fastapi-0.0.2.dist-info/LICENSE
flask_fastapi-0.0.2.dist-info/METADATA
flask_fastapi-0.0.2.dist-info/WHEEL
flask_fastapi-0.0.2.dist-info/RECORD
