Metadata-Version: 2.1
Name: flask-fastapi
Version: 0.0.2
Summary: Extended version of Flask to offer FastAPI inspired functionality.
Author: Matt Wilson
Author-email: matt@callmematt.com
Requires-Python: >=3.11,<4.0
Classifier: Programming Language :: Python :: 3
Classifier: Programming Language :: Python :: 3.11
Requires-Dist: flask (>=3.0.3,<4.0.0)
Requires-Dist: orjson (>=3.10.3,<4.0.0)
Requires-Dist: pydantic (>=2.7.3,<3.0.0)
Requires-Dist: pyyaml (>=6.0.1,<7.0.0)
